setup.py
transi2p/__init__.py
transi2p.egg-info/PKG-INFO
transi2p.egg-info/SOURCES.txt
transi2p.egg-info/dependency_links.txt
transi2p.egg-info/requires.txt
transi2p.egg-info/top_level.txt
twisted/plugins/transi2p_plugin.py