Metadata-Version: 1.0
Name: transi2p
Version: 1.2.3
Summary: Transparent proxy for i2p.
Home-page: https://github.com/rbif/transi2p/
Author: Arnold French
Author-email: arnold.french1974@yandex.com
License: UNKNOWN
Platform: UNKNOWN
